dbt_protos-1.0.335.dist-info/licenses/LICENSE
dbtlabs/proto/public/v1/py.typed
dbtlabs/proto/public/v1/common/vortex_options_pb2.py
dbtlabs/proto/public/v1/common/vortex_options_pb2.pyi
dbtlabs/proto/public/v1/common/vortex_options_pb2_grpc.py
dbtlabs/proto/public/v1/common/vortex_telemetry_contexts_pb2.py
dbtlabs/proto/public/v1/common/vortex_telemetry_contexts_pb2.pyi
dbtlabs/proto/public/v1/common/vortex_telemetry_contexts_pb2_grpc.py
dbtlabs/proto/public/v1/events/insights_pb2.py
dbtlabs/proto/public/v1/events/insights_pb2.pyi
dbtlabs/proto/public/v1/events/insights_pb2_grpc.py
dbtlabs/proto/public/v1/events/mcp_pb2.py
dbtlabs/proto/public/v1/events/mcp_pb2.pyi
dbtlabs/proto/public/v1/events/mcp_pb2_grpc.py
dbtlabs/proto/public/v1/events/metadata_telemetry_pb2.py
dbtlabs/proto/public/v1/events/metadata_telemetry_pb2.pyi
dbtlabs/proto/public/v1/events/metadata_telemetry_pb2_grpc.py
dbtlabs/proto/public/v1/events/py.typed
dbtlabs/proto/public/v1/events/vortex_pb2.py
dbtlabs/proto/public/v1/events/vortex_pb2.pyi
dbtlabs/proto/public/v1/events/vortex_pb2_grpc.py
dbtlabs/proto/public/v1/events/vscode_pb2.py
dbtlabs/proto/public/v1/events/vscode_pb2.pyi
dbtlabs/proto/public/v1/events/vscode_pb2_grpc.py
dbtlabs/proto/public/v1/fields/adapter_types_pb2.py
dbtlabs/proto/public/v1/fields/adapter_types_pb2.pyi
dbtlabs/proto/public/v1/fields/adapter_types_pb2_grpc.py
dbtlabs/proto/public/v1/fields/common_types_pb2.py
dbtlabs/proto/public/v1/fields/common_types_pb2.pyi
dbtlabs/proto/public/v1/fields/common_types_pb2_grpc.py
dbtlabs/proto/public/v1/fields/core_types_pb2.py
dbtlabs/proto/public/v1/fields/core_types_pb2.pyi
dbtlabs/proto/public/v1/fields/core_types_pb2_grpc.py
dbtlabs/proto/public/v1/fields/py.typed
dbtlabs/proto/public/v1/fields/vscode_types_pb2.py
dbtlabs/proto/public/v1/fields/vscode_types_pb2.pyi
dbtlabs/proto/public/v1/fields/vscode_types_pb2_grpc.py
dbtlabs/proto/public/v1/records/py.typed
test/import_test.py
dbt_protos-1.0.335.dist-info/METADATA
dbt_protos-1.0.335.dist-info/WHEEL
dbt_protos-1.0.335.dist-info/top_level.txt
dbt_protos-1.0.335.dist-info/RECORD
