Metadata-Version: 2.4
Name: dbt-protos
Version: 1.0.335
Summary: Public proto bindings for dbt
Home-page: https://github.com/dbt-labs/proto-python-public
Author: dbt Labs, Inc.
Author-email: info@dbtlabs.com
License: Apache-2.0
Classifier: Programming Language :: Python :: 3
Classifier: Operating System :: OS Independent
Classifier: License :: OSI Approved :: Apache Software License
Requires-Python: >=3.6
License-File: LICENSE
Requires-Dist: protobuf>=3.17.1
Dynamic: author
Dynamic: author-email
Dynamic: classifier
Dynamic: description
Dynamic: description-content-type
Dynamic: home-page
Dynamic: license
Dynamic: license-file
Dynamic: requires-dist
Dynamic: requires-python
Dynamic: summary
